MANIFEST.in
README.rst
setup.py
docs/HISTORY.txt
docs/LICENSE.GPL
docs/LICENSE.txt
docs/screenshot_default_from.png
docs/screenshot_default_to.png
docs/screenshot_other1.png
docs/screenshot_other2.png
docs/screenshot_slider.png
ftw/__init__.py
ftw.mobilenavigation.egg-info/PKG-INFO
ftw.mobilenavigation.egg-info/SOURCES.txt
ftw.mobilenavigation.egg-info/dependency_links.txt
ftw.mobilenavigation.egg-info/entry_points.txt
ftw.mobilenavigation.egg-info/namespace_packages.txt
ftw.mobilenavigation.egg-info/not-zip-safe
ftw.mobilenavigation.egg-info/requires.txt
ftw.mobilenavigation.egg-info/top_level.txt
ftw/mobilenavigation/__init__.py
ftw/mobilenavigation/configure.zcml
ftw/mobilenavigation/resources.zcml
ftw/mobilenavigation/testing.py
ftw/mobilenavigation/Extensions/__init__.py
ftw/mobilenavigation/Extensions/install.py
ftw/mobilenavigation/browser/__init__.py
ftw/mobilenavigation/browser/configure.zcml
ftw/mobilenavigation/browser/navigation.py
ftw/mobilenavigation/browser/slider.pt
ftw/mobilenavigation/browser/resources/collapse-navi.png
ftw/mobilenavigation/browser/resources/expand-navi.png
ftw/mobilenavigation/browser/resources/expand_navigation.js
ftw/mobilenavigation/browser/resources/mobile_buttons.png
ftw/mobilenavigation/browser/resources/navigation.css
ftw/mobilenavigation/browser/resources/navigation.js
ftw/mobilenavigation/browser/resources/slide-back.png
ftw/mobilenavigation/browser/resources/slide_navigation.js
ftw/mobilenavigation/browser/resources/spinner.gif
ftw/mobilenavigation/browser/resources/spinner_big.gif
ftw/mobilenavigation/browser/resources/scss/mobilenavigation.scss
ftw/mobilenavigation/locales/ftw.mobilenavigation.pot
ftw/mobilenavigation/locales/de/LC_MESSAGES/ftw.mobilenavigation.po
ftw/mobilenavigation/profiles/default/actions.xml
ftw/mobilenavigation/profiles/default/cssregistry.xml
ftw/mobilenavigation/profiles/default/jsregistry.xml
ftw/mobilenavigation/profiles/default/metadata.xml
ftw/mobilenavigation/profiles/default/viewlets.xml
ftw/mobilenavigation/profiles/slide/actions.xml
ftw/mobilenavigation/profiles/slide/jsregistry.xml
ftw/mobilenavigation/profiles/slide/metadata.xml
ftw/mobilenavigation/profiles/uninstall/actions.xml
ftw/mobilenavigation/profiles/uninstall/cssregistry.xml
ftw/mobilenavigation/profiles/uninstall/jsregistry.xml
