Metadata-Version: 1.1
Name: ftw.mobilenavigation
Version: 1.4.5
Summary: Defines a special navigation.
Home-page: https://github.com/4teamwork/ftw.mobilenavigation
Author: Julian Infanger
Author-email: mailto:info@4teamwork.ch
License: GPL2
Keywords: plone ftw content templates
Platform: UNKNOWN
Classifier: Framework :: Plone
Classifier: Framework :: Plone :: 4.1
Classifier: Framework :: Plone :: 4.2
Classifier: Framework :: Plone :: 4.3
Classifier: Programming Language :: Python
Classifier: Topic :: Software Development :: Libraries :: Python Modules
